silverbp_jfrog/__init__.py
silverbp_jfrog/artifactory.py
silverbp_jfrog-0.5.4.dist-info/DESCRIPTION.rst
silverbp_jfrog-0.5.4.dist-info/METADATA
silverbp_jfrog-0.5.4.dist-info/RECORD
silverbp_jfrog-0.5.4.dist-info/WHEEL
silverbp_jfrog-0.5.4.dist-info/metadata.json
silverbp_jfrog-0.5.4.dist-info/top_level.txt
