Metadata-Version: 2.0
Name: silverbp-jfrog
Version: 0.5.4
Summary: Python API for interacting with JFrog Apis
Home-page: https://github.com/silverbp/pypi-jfrog
Author: Silver Blueprints LLC
Author-email: admin@silverblueprints.com
License: MIT
Platform: UNKNOWN
